gh_project_v2/__init__.py
gh_project_v2/client.py
gh_project_v2/clients.py
gh_project_v2/exceptions.py
gh_project_v2/models/__init__.py
gh_project_v2/models/comment.py
gh_project_v2/models/draft_issue.py
gh_project_v2/models/event.py
gh_project_v2/models/events/__init__.py
gh_project_v2/models/events/added_to_project_event.py
gh_project_v2/models/events/assigned_event.py
gh_project_v2/models/events/closed_event.py
gh_project_v2/models/events/comment_deleted_event.py
gh_project_v2/models/events/cross_referenced_event.py
gh_project_v2/models/events/demilestoned_event.py
gh_project_v2/models/events/event.py
gh_project_v2/models/events/issue_comment_event.py
gh_project_v2/models/events/issue_type_added_event.py
gh_project_v2/models/events/issue_type_changed_event.py
gh_project_v2/models/events/issue_type_removed_event.py
gh_project_v2/models/events/labeled_event.py
gh_project_v2/models/events/locked_event.py
gh_project_v2/models/events/marked_as_duplicate_event.py
gh_project_v2/models/events/mentioned_event.py
gh_project_v2/models/events/merged_event.py
gh_project_v2/models/events/milestoned_event.py
gh_project_v2/models/events/moved_columns_in_project_event.py
gh_project_v2/models/events/parent_issue_added_event.py
gh_project_v2/models/events/parent_issue_removed_event.py
gh_project_v2/models/events/pinned_event.py
gh_project_v2/models/events/referenced_event.py
gh_project_v2/models/events/renamed_title_event.py
gh_project_v2/models/events/reopened_event.py
gh_project_v2/models/events/sub_issue_added_event.py
gh_project_v2/models/events/sub_issue_removed_event.py
gh_project_v2/models/events/subscribed_event.py
gh_project_v2/models/events/transferred_event.py
gh_project_v2/models/events/unassigned_event.py
gh_project_v2/models/events/unlabeled_event.py
gh_project_v2/models/events/unsubscribed_event.py
gh_project_v2/models/field.py
gh_project_v2/models/issue.py
gh_project_v2/models/label.py
gh_project_v2/models/milestone.py
gh_project_v2/models/option.py
gh_project_v2-0.1.6.dist-info/LICENSE
gh_project_v2-0.1.6.dist-info/METADATA
gh_project_v2-0.1.6.dist-info/WHEEL
gh_project_v2-0.1.6.dist-info/RECORD
