Metadata-Version: 2.3
Name: gh-project-v2
Version: 0.1.6
Summary: Python module for working with GitHub GraphQL API, focusing on ProjectsV2
License: MIT
Keywords: github,graphql,api,projects,projectsv2,automation
Author: psec.io
Author-email: info@psec.io
Requires-Python: >=3.8
Classifier: Development Status :: 4 - Beta
Classifier: Intended Audience :: Developers
Classifier: License :: OSI Approved :: MIT License
Classifier: Programming Language :: Python :: 3
Classifier: Programming Language :: Python :: 3.8
Classifier: Programming Language :: Python :: 3.9
Classifier: Programming Language :: Python :: 3.10
Classifier: Programming Language :: Python :: 3.11
Classifier: Programming Language :: Python :: 3.12
Classifier: Topic :: Software Development :: Libraries :: Python Modules
Classifier: Topic :: Internet :: WWW/HTTP :: Dynamic Content
Classifier: Topic :: System :: Systems Administration
Provides-Extra: dev
Requires-Dist: PyJWT (>=2.0.0)
Requires-Dist: black (>=22.0.0) ; extra == "dev"
Requires-Dist: flake8 (>=3.9.0) ; extra == "dev"
Requires-Dist: jinja2 (>=3.0.0)
Requires-Dist: pytest (>=6.0.0) ; extra == "dev"
Requires-Dist: pytest-mock (>=3.14.0) ; extra == "dev"
Requires-Dist: requests (>=2.25.0)
Project-URL: Documentation, https://github.com/psecio/gh-project-v2#readme
Project-URL: Homepage, https://github.com/psecio/gh-project-v2
Project-URL: Issues, https://github.com/psecio/gh-project-v2/issues
Project-URL: Repository, https://github.com/psecio/gh-project-v2
